README
setup.py
subtitler/__init__.py
subtitler/subtitler.py
subtitler.egg-info/PKG-INFO
subtitler.egg-info/SOURCES.txt
subtitler.egg-info/dependency_links.txt
subtitler.egg-info/entry_points.txt
subtitler.egg-info/top_level.txt