Metadata-Version: 1.0
Name: subtitler
Version: 0.2.1
Summary: Tool/library for searching subtitles by hash or typed query.
Home-page: https://github.com/creckx/Subtitler
Author: Adam Strauch
Author-email: cx@initd.cz
License: BSD
Keywords: subtitle subtitles
Platform: UNKNOWN
Classifier: Development Status :: 3 - Alpha
Classifier: Topic :: Utilities
Classifier: License :: OSI Approved :: BSD License
